<panel>
	<attachment_group class="vertical_arrange_autosize_horizontal_centre" vertical_alignment="top" vertical_gap="4" vertical_inset="0"/>

	<boolean id="should_force_refresh" value="true"/>

	<container width="140" height="140">
		<attachment_group class="horizontal_arrange" vertical_inset="0" vertical_offset="12" horizontal_inset="0" horizontal_offset="10"/>

		<!-- portrait -->
		<widget class="object_portrait_picture" width="130" height="130" scale_picture="true" keep_aspect_ratio="true" image_alignment="centre">
			<record id="object_property">
				<integer id="get_property" value="Pers"/>
				<boolean id="dont_set_object" value="true"/>
				<boolean id="dont_set_hint" value="true"/>
			</record>
			<layout class="stick_to_sides_attachment" alignment="vertical" inset="0"/>
		</widget>

		<!-- currently speaking icon? -->
		<widget class="picture" file="icons/custom/quick chat/quick_chat_speaking_mask_square_remote" scale_picture="true" keep_aspect_ratio="true" width="70" height="70" image_alignment="centre" red_replacement="red 900">
			<layout class="stick_to_sides_attachment" alignment="all" inset="0"/>
		</widget>
	</container>

	<!-- name -->
	<widget class="person_button" colour="black" id="perb" size="large" style="bold" alignment="left, centre_y" auto_size="all" auto_size_maximum_width="180" info_popup_enabled="false"/>

	<!-- current team -->
	<widget class="team_button" icon_enabled="true" size="small" colour="faded text" auto_size="all">
		<record id="object_property">
			<integer id="get_property" value="PcMt"/>
			<boolean id="dont_set_object" value="true"/>
		</record>
	</widget>

	<!-- description -->
	<widget class="text" id="Pdes" size="small" colour="faded text" auto_size="vertical" multiline="true" alignment="centre_y">
		<layout class="stick_to_sides_attachment" alignment="horizontal" inset="0"/>
	</widget>

</panel>